libname/__init__.py
libname/hello.py
ratzethellopkg01-0.0.1.dist-info/METADATA
ratzethellopkg01-0.0.1.dist-info/WHEEL
ratzethellopkg01-0.0.1.dist-info/top_level.txt
ratzethellopkg01-0.0.1.dist-info/RECORD
