Metadata-Version: 2.1
Name: ratzethellopkg01
Version: 0.0.1
Summary: This package prints your name and asks question.
Author: Abhishek Raturi (ratzet)
Author-email: abhishek.raturi6@gmail.com
License: UNKNOWN
Keywords: hello
Platform: UNKNOWN
Classifier: Development Status :: 1 - Planning
Classifier: Intended Audience :: Developers
Classifier: Programming Language :: Python :: 3
Classifier: Operating System :: Unix
Classifier: Operating System :: MacOS :: MacOS X
Classifier: Operating System :: Microsoft :: Windows
